LICENSE
MANIFEST.in
README.rst
setup.py
flask_utilities/__init__.py
flask_utilities.egg-info/PKG-INFO
flask_utilities.egg-info/SOURCES.txt
flask_utilities.egg-info/dependency_links.txt
flask_utilities.egg-info/requires.txt
flask_utilities.egg-info/top_level.txt
flask_utilities/fields/__init__.py
flask_utilities/fields/email.py
flask_utilities/models/__init__.py
flask_utilities/models/representation_model.py
flask_utilities/resources/__init__.py
flask_utilities/resources/authenticated.py
flask_utilities/validators/__init__.py
flask_utilities/validators/custom_validator.py